test_datasets_2/__init__.py
test_datasets_2/dataloaders.py
test_datasets_2/utils.py
test_datasets_2/data/__init__.py
test_datasets_2/data/HouseTwenty/HouseTwenty_TEST.tsv
test_datasets_2/data/HouseTwenty/HouseTwenty_TRAIN.tsv
test_datasets_2/data/HouseTwenty/__init__.py
test_datasets_2/data/InlineSkate/InlineSkate_TEST.tsv
test_datasets_2/data/InlineSkate/InlineSkate_TRAIN.tsv
test_datasets_2/data/InlineSkate/__init__.py
test_datasets_2/data/InsectEPGRegularTrain/InsectEPGRegularTrain_TEST.tsv
test_datasets_2/data/InsectEPGRegularTrain/InsectEPGRegularTrain_TRAIN.tsv
test_datasets_2/data/InsectEPGRegularTrain/__init__.py
test_datasets_2/data/InsectEPGSmallTrain/InsectEPGSmallTrain_TEST.tsv
test_datasets_2/data/InsectEPGSmallTrain/InsectEPGSmallTrain_TRAIN.tsv
test_datasets_2/data/InsectEPGSmallTrain/__init__.py
test_datasets_2/data/InsectWingbeatSound/InsectWingbeatSound_TEST.tsv
test_datasets_2/data/InsectWingbeatSound/InsectWingbeatSound_TRAIN.tsv
test_datasets_2/data/InsectWingbeatSound/__init__.py
test_datasets_2/data/ItalyPowerDemand/ItalyPowerDemand_TEST.tsv
test_datasets_2/data/ItalyPowerDemand/ItalyPowerDemand_TRAIN.tsv
test_datasets_2/data/ItalyPowerDemand/__init__.py
test_datasets_2/data/LargeKitchenAppliances/LargeKitchenAppliances_TEST.tsv
test_datasets_2/data/LargeKitchenAppliances/LargeKitchenAppliances_TRAIN.tsv
test_datasets_2/data/LargeKitchenAppliances/__init__.py
test_datasets_2/data/Lightning2/Lightning2_TEST.tsv
test_datasets_2/data/Lightning2/Lightning2_TRAIN.tsv
test_datasets_2/data/Lightning2/__init__.py
test_datasets_2/data/Lightning7/Lightning7_TEST.tsv
test_datasets_2/data/Lightning7/Lightning7_TRAIN.tsv
test_datasets_2/data/Lightning7/__init__.py
test_datasets_2/data/Mallat/Mallat_TEST.tsv
test_datasets_2/data/Mallat/Mallat_TRAIN.tsv
test_datasets_2/data/Mallat/__init__.py
test_datasets_2/data/Meat/Meat_TEST.tsv
test_datasets_2/data/Meat/Meat_TRAIN.tsv
test_datasets_2/data/Meat/__init__.py
test_datasets_2-0.0.2.dist-info/METADATA
test_datasets_2-0.0.2.dist-info/WHEEL
test_datasets_2-0.0.2.dist-info/top_level.txt
test_datasets_2-0.0.2.dist-info/RECORD
