Metadata-Version: 2.1
Name: test-datasets-2
Version: 0.0.2
Summary: A small package for handling and loading univariate ucr timeseries datasets
Author: JavidanAbdullayev (Javidan Abdullayev)
Author-email: <javidan.abdullayev@uha.fr>
Classifier: Development Status :: 1 - Planning
Classifier: Intended Audience :: Developers
Classifier: Programming Language :: Python :: 3
Classifier: Operating System :: Unix
Classifier: Operating System :: MacOS :: MacOS X
Classifier: Operating System :: Microsoft :: Windows
Requires-Dist: pandas
Requires-Dist: importlib
